Metadata-Version: 2.1
Name: munqu
Version: 0.1.0
Summary: MUNQU library.
Author: P. Martínez-Rodríguez
Author-email: razonqritica@gmail.com
Requires-Python: >=3.12,<4.0
Classifier: Programming Language :: Python :: 3
Classifier: Programming Language :: Python :: 3.12
Requires-Dist: matplotlib (>=3.8.3,<4.0.0)
Requires-Dist: numpy (>=1.26.4,<2.0.0)
Requires-Dist: pandas (>=2.2.1,<3.0.0)
Requires-Dist: scikit-opt (>=0.6.6,<0.7.0)
Requires-Dist: scipy (>=1.12.0,<2.0.0)
